dytools/__init__.py
dytools/time_tool.py
dytools-0.1.dist-info/LICENSE
dytools-0.1.dist-info/METADATA
dytools-0.1.dist-info/WHEEL
dytools-0.1.dist-info/top_level.txt
dytools-0.1.dist-info/RECORD
