Metadata-Version: 2.1
Name: dytools
Version: 0.1
Summary: A Python toolkit
Home-page: https://gitee.com/dyliujun/dytools.git
Author: liujun
Author-email: shjpl23801@163.com
License: MIT
License-File: LICENSE
